gamedriver/__init__.py
gamedriver/_error.py
gamedriver/_geometry.py
gamedriver/_locate.py
gamedriver/_match_template.py
gamedriver/_tap_img.py
gamedriver/_util.py
gamedriver/logger.py
gamedriver/settings.py
gamedriver-1.1.0.dist-info/METADATA
gamedriver-1.1.0.dist-info/WHEEL
gamedriver-1.1.0.dist-info/licenses/LICENSE
gamedriver-1.1.0.dist-info/RECORD
