Metadata-Version: 2.3
Name: gamedriver
Version: 1.1.0
Summary: Lightweight cross-platform image matching tools focused on automation
Project-URL: Homepage, https://github.com/aentwist/gamedriver
Project-URL: Issues, https://github.com/aentwist/gamedriver/issues
Author: Anderson Entwistle
License-File: LICENSE
Keywords: automation,computer vision,game,image detection,image matching,opencv,simulation,template matching,testing
Classifier: License :: OSI Approved :: GNU General Public License v3 (GPLv3)
Classifier: Operating System :: OS Independent
Classifier: Programming Language :: Python :: 3
Requires-Python: ~=3.9
Requires-Dist: numpy~=2.0
Requires-Dist: python-json-logger~=2.0
Provides-Extra: all
Requires-Dist: build; extra == 'all'
Requires-Dist: coverage; extra == 'all'
Requires-Dist: matplotlib; extra == 'all'
Requires-Dist: opencv-python-headless~=4.0; extra == 'all'
Requires-Dist: pip-tools; extra == 'all'
Requires-Dist: pipdeptree; extra == 'all'
Requires-Dist: pytest; extra == 'all'
Requires-Dist: sphinx; extra == 'all'
Requires-Dist: sphinxcontrib-fulltoc; extra == 'all'
Requires-Dist: twine; extra == 'all'
Requires-Dist: ufmt; extra == 'all'
Requires-Dist: validate-pyproject[all]; extra == 'all'
Provides-Extra: dev
Requires-Dist: build; extra == 'dev'
Requires-Dist: coverage; extra == 'dev'
Requires-Dist: matplotlib; extra == 'dev'
Requires-Dist: pip-tools; extra == 'dev'
Requires-Dist: pipdeptree; extra == 'dev'
Requires-Dist: pytest; extra == 'dev'
Requires-Dist: sphinx; extra == 'dev'
Requires-Dist: sphinxcontrib-fulltoc; extra == 'dev'
Requires-Dist: twine; extra == 'dev'
Requires-Dist: ufmt; extra == 'dev'
Requires-Dist: validate-pyproject[all]; extra == 'dev'
Provides-Extra: opencv-python
Requires-Dist: opencv-python~=4.0; extra == 'opencv-python'
Provides-Extra: opencv-python-headless
Requires-Dist: opencv-python-headless~=4.0; extra == 'opencv-python-headless'
